<?xml version="1.0" encoding="utf-8"?>
<ProjectResults><GoalsData><Goal><Name>GG Force 1</Name><Value>10.011384442507143</Value><AverageValue>9.9851934610943367</AverageValue></Goal><Goal><Name>GG Force (X) 2</Name><Value>0.0035013201232303986</Value><AverageValue>0.23452795695252734</AverageValue></Goal><Goal><Name>GG Force (Y) 3</Name><Value>-10.008746148680023</Value><AverageValue>-9.9749250504927254</AverageValue></Goal><Goal><Name>GG Force (Z) 4</Name><Value>0.22979714470432147</Value><AverageValue>0.36453038861946169</AverageValue></Goal><Goal><Name>SG Normal Force 1</Name><Value>0.11675615464077667</Value><AverageValue>0.11635844479669781</AverageValue></Goal><Goal><Name>SG Torque (X) 2</Name><Value>-0.0072723925433621278</Value><AverageValue>-0.0072407647629473158</AverageValue></Goal><Goal><Name>SG Torque (Y) 3</Name><Value>0.022611256975139601</Value><AverageValue>0.022534922300560128</AverageValue></Goal><Goal><Name>SG Torque (Z) 4</Name><Value>0.0033356902453698404</Value><AverageValue>0.0033142431136361605</AverageValue></Goal></GoalsData></ProjectResults>