<?xml version="1.0" encoding="utf-8"?>
<ProjectResults><GoalsData><Goal><Name>GG Force 1</Name><Value>2.5187733687714857</Value><AverageValue>2.5217382696888158</AverageValue></Goal><Goal><Name>GG Force (X) 2</Name><Value>-0.0040904083266754951</Value><AverageValue>-0.0020300613271307436</AverageValue></Goal><Goal><Name>GG Force (Y) 3</Name><Value>-2.5176375141700236</Value><AverageValue>-2.5209167583934682</AverageValue></Goal><Goal><Name>GG Force (Z) 4</Name><Value>0.075524161934862499</Value><AverageValue>0.061671331027300304</AverageValue></Goal><Goal><Name>SG Normal Force 1</Name><Value>0.023003224325144966</Value><AverageValue>0.022998171816944385</AverageValue></Goal><Goal><Name>SG Torque (X) 2</Name><Value>-0.0012913883609756856</Value><AverageValue>-0.0012885973373607472</AverageValue></Goal><Goal><Name>SG Torque (Y) 3</Name><Value>0.0045623388349208868</Value><AverageValue>0.0045615830308320228</AverageValue></Goal><Goal><Name>SG Torque (Z) 4</Name><Value>0.00057862147236563389</Value><AverageValue>0.00057543396868834067</AverageValue></Goal></GoalsData></ProjectResults>